pyeznacl/__init__.py
pyeznacl/cryptostring.py
pyeznacl/encryption.py
pyeznacl/ezhash.py
pyeznacl-1.0.0.dist-info/LICENSE
pyeznacl-1.0.0.dist-info/WHEEL
pyeznacl-1.0.0.dist-info/METADATA
pyeznacl-1.0.0.dist-info/RECORD
