Metadata-Version: 2.1
Name: pyeznacl
Version: 1.0.0
Summary: A wrapper around PyNaCl to make it even easier to use
Keywords: nacl,encryption,cryptostring
Author-email: Jon Yoder <jon@yoder.cloud>
Requires-Python: >=3.6
Classifier: License :: OSI Approved :: MIT License
Classifier: Development Status :: 5 - Production/Stable
Classifier: Intended Audience :: Developers
Classifier: Topic :: Communications
Requires-Dist: jsonschema>=4.3.3
Requires-Dist: retval>=1.0.0
Requires-Dist: PyNaCl>=1.3.0
Requires-Dist: blake3>=0.2.1
